{
    "@class": "com.kony.gen.viz.model.component.KVizLabel",
    "DNDConfig": null,
    "_margin_": [
        1,
        3,
        1,
        1
    ],
    "_padding_": [
        1,
        1,
        1,
        1
    ],
    "_skin_": "s68006200fca4579b33d77b0f8d4750e",
    "_text_": "Session Expired, please login",
    "_wrapping_": 2,
    "android": {
        "textStyle": {
            "letterSpacing": 0,
            "strikeThrough": false
        }
    },
    "canUpdateUI": true,
    "containerweight": 100,
    "contentalignment": 5,
    "id": "lblPopTxt",
    "info": null,
    "ipad": {
        "psp": {
            "wrapping": 2
        }
    },
    "iphone": {
        "psp": {
            "wrapping": 2
        }
    },
    "isvisible": true,
    "kuid": "hb4b8d51bc104cb1ad8189279dba18fd",
    "margininpixel": false,
    "name": "kony.ui.Label",
    "paddinginpixel": false,
    "parent": "popupSessionExp",
    "pf": "popupSessionExp",
    "textstyle": {},
    "tooltip": "",
    "wType": "Label"
}